cosmosdb_bulk_updater/__init__.py
cosmosdb_bulk_updater/bulk_updater.py
cosmosdb_bulk_updater-0.5.0.dist-info/LICENSE
cosmosdb_bulk_updater-0.5.0.dist-info/METADATA
cosmosdb_bulk_updater-0.5.0.dist-info/WHEEL
cosmosdb_bulk_updater-0.5.0.dist-info/top_level.txt
cosmosdb_bulk_updater-0.5.0.dist-info/RECORD
