Metadata-Version: 2.1
Name: cosmosdb-bulk-updater
Version: 0.5.0
Summary: A bulk updater for Microsoft CosmosDB
Home-page: https://github.com/renato04/cosmosdb-bulk-updater
Author: Renato Ramos
Author-email: ramos.renato@outlook.com
License: UNKNOWN
Platform: UNKNOWN
Classifier: Programming Language :: Python :: 3
Classifier: License :: OSI Approved :: MIT License
Classifier: Operating System :: OS Independent
